postman_drf/__init__.py
postman_drf/__main__.py
postman_drf/cli.py
postman_drf/exceptions.py
postman_drf/file_manager.py
postman_drf/generator.py
postman_drf/main.py
postman_drf/parsers.py
postman_drf/validators.py
postman_drf-0.1.1.dist-info/LICENSE
postman_drf-0.1.1.dist-info/METADATA
postman_drf-0.1.1.dist-info/WHEEL
postman_drf-0.1.1.dist-info/top_level.txt
postman_drf-0.1.1.dist-info/RECORD
