Metadata-Version: 2.1
Name: postman-drf
Version: 0.1.1
Summary: A package to convert Postman collections to Django rest framework code and vice versa.
Home-page: https://github.com/HasanAdeli/postman-drf
Author: Hassan adeli
Author-email: hasanadeli1374@gmail.com
Classifier: Programming Language :: Python :: 3
Classifier: License :: OSI Approved :: MIT License
Classifier: Operating System :: OS Independent
Requires-Python: >=3.7
License-File: LICENSE
Requires-Dist: typer
